LICENSE
README.md
pyproject.toml
setup.py
LeagueOfEvents.egg-info/PKG-INFO
LeagueOfEvents.egg-info/SOURCES.txt
LeagueOfEvents.egg-info/dependency_links.txt
LeagueOfEvents.egg-info/requires.txt
LeagueOfEvents.egg-info/top_level.txt
leagueofevents/__init__.py
leagueofevents/api.py
leagueofevents/events.py
leagueofevents/helpers.py
leagueofevents/leagueofevents.py