Metadata-Version: 2.1
Name: LeagueOfEvents
Version: 1.0.7
Summary: Create an event system for the League of Legends live game API
Home-page: https://github.com/agroth01/LeagueOfEvents
Author: Alexander Groth
Author-email: software.agroth@gmail.com
License: UNKNOWN
Platform: UNKNOWN
Requires-Python: >=3.8
License-File: LICENSE
